{
  "_comment": "Canonical category taxonomy. Slugs and Korean/English names are LOCKED once added. Gemini adds new entries automatically (max 3/week). For manual edits: only add or remove rows — never rename existing ones (breaks rank-change tracking).",
  "max_new_per_week": 3,
  "updated_at": "2026-05-26T00:00:00.000Z",
  "categories": [
    { "slug": "kpop-goods",            "name_kr": "K-POP 굿즈/포토카드",   "name_en": "K-POP Goods & Photocards", "added": "2026-05-26" },
    { "slug": "character-goods",       "name_kr": "캐릭터 굿즈",            "name_en": "Character Goods",          "added": "2026-05-26" },
    { "slug": "webtoon-goods",         "name_kr": "웹툰 굿즈",              "name_en": "Webtoon Goods",            "added": "2026-05-26" },
    { "slug": "kdrama-goods",          "name_kr": "K-드라마 굿즈",          "name_en": "K-Drama Goods",            "added": "2026-05-26" },
    { "slug": "k-beauty-skincare",     "name_kr": "K-뷰티 (스킨케어)",      "name_en": "K-Beauty Skincare",        "added": "2026-05-26" },
    { "slug": "k-beauty-makeup",       "name_kr": "K-뷰티 (색조)",          "name_en": "K-Beauty Makeup",          "added": "2026-05-26" },
    { "slug": "k-beauty-haircare",     "name_kr": "K-뷰티 (헤어케어)",      "name_en": "K-Beauty Haircare",        "added": "2026-05-26" },
    { "slug": "k-beauty-devices",      "name_kr": "K-뷰티 디바이스",        "name_en": "K-Beauty Devices",         "added": "2026-05-26" },
    { "slug": "inner-beauty",          "name_kr": "이너뷰티/건강기능식품",  "name_en": "Inner Beauty & Supplements","added": "2026-05-26" },
    { "slug": "k-fashion",             "name_kr": "K-패션/리셀",            "name_en": "K-Fashion & Resell",       "added": "2026-05-26" },
    { "slug": "mens-fashion",          "name_kr": "남성 패션 잡화",         "name_en": "Men's Fashion Accessories","added": "2026-05-26" },
    { "slug": "modern-hanbok",         "name_kr": "한복 모던",              "name_en": "Modern Hanbok",            "added": "2026-05-26" },
    { "slug": "auto-parts",            "name_kr": "자동차 부품",            "name_en": "Auto Parts",               "added": "2026-05-26" },
    { "slug": "auto-accessories",      "name_kr": "자동차 액세서리",        "name_en": "Auto Accessories",         "added": "2026-05-26" },
    { "slug": "drones",                "name_kr": "드론/액세서리",          "name_en": "Drones & Accessories",     "added": "2026-05-26" },
    { "slug": "smartphone-acc",        "name_kr": "스마트폰 액세서리",      "name_en": "Smartphone Accessories",   "added": "2026-05-26" },
    { "slug": "computer-parts",        "name_kr": "컴퓨터 부품/주변기기",   "name_en": "Computer Parts & Peripherals","added": "2026-05-26" },
    { "slug": "k-stationery",          "name_kr": "K-문구/다꾸",            "name_en": "K-Stationery & Diary Deco","added": "2026-05-26" },
    { "slug": "trading-cards",         "name_kr": "수집용 트레이딩 카드",   "name_en": "Trading Cards",            "added": "2026-05-26" },
    { "slug": "figures-collectibles",  "name_kr": "피규어/수집용 완구",     "name_en": "Figures & Collectible Toys","added": "2026-05-26" },
    { "slug": "lego-blocks",           "name_kr": "조립 완구/레고",         "name_en": "LEGO & Building Blocks",   "added": "2026-05-26" },
    { "slug": "esports-merch",         "name_kr": "e스포츠 굿즈",           "name_en": "E-Sports Merch",           "added": "2026-05-26" },
    { "slug": "k-food",                "name_kr": "K-푸드/스낵",            "name_en": "K-Food & Snacks",          "added": "2026-05-26" },
    { "slug": "kitchen-ware",          "name_kr": "K-주방용품",             "name_en": "Korean Kitchenware",       "added": "2026-05-26" },
    { "slug": "home-decor",            "name_kr": "K-홈데코",               "name_en": "Korean Home Decor",        "added": "2026-05-26" },
    { "slug": "camping-gear",          "name_kr": "캠핑/아웃도어",          "name_en": "Camping & Outdoor",        "added": "2026-05-26" },
    { "slug": "golf-gear",             "name_kr": "골프 용품",              "name_en": "Golf Equipment",           "added": "2026-05-26" },
    { "slug": "fishing-gear",          "name_kr": "낚시 용품",              "name_en": "Fishing Equipment",        "added": "2026-05-26" },
    { "slug": "pet-supplies",          "name_kr": "반려동물 용품",          "name_en": "Pet Supplies",             "added": "2026-05-26" },
    { "slug": "traditional-craft",     "name_kr": "전통 공예품",            "name_en": "Traditional Craft",        "added": "2026-05-26" }
  ]
}
